jupyterlab_sparkmonitor-4.1.0.data/data/etc/jupyter/jupyter_server_config.d/jupyterlab_sparkmonitor.json
jupyterlab_sparkmonitor-4.1.0.data/data/share/jupyter/labextensions/jupyterlab-sparkmonitor/install.json
jupyterlab_sparkmonitor-4.1.0.data/data/share/jupyter/labextensions/jupyterlab-sparkmonitor/package.json
jupyterlab_sparkmonitor-4.1.0.data/data/share/jupyter/labextensions/jupyterlab-sparkmonitor/static/555.2486da0405d90759fa59.js
jupyterlab_sparkmonitor-4.1.0.data/data/share/jupyter/labextensions/jupyterlab-sparkmonitor/static/555.2486da0405d90759fa59.js.LICENSE.txt
jupyterlab_sparkmonitor-4.1.0.data/data/share/jupyter/labextensions/jupyterlab-sparkmonitor/static/568.58caea7cc19fed3b7601.js
jupyterlab_sparkmonitor-4.1.0.data/data/share/jupyter/labextensions/jupyterlab-sparkmonitor/static/568.58caea7cc19fed3b7601.js.LICENSE.txt
jupyterlab_sparkmonitor-4.1.0.data/data/share/jupyter/labextensions/jupyterlab-sparkmonitor/static/700.8a51fb45cd33c6e7d2f0.js
jupyterlab_sparkmonitor-4.1.0.data/data/share/jupyter/labextensions/jupyterlab-sparkmonitor/static/755.b0c8069fab2b94b3c4ac.js
jupyterlab_sparkmonitor-4.1.0.data/data/share/jupyter/labextensions/jupyterlab-sparkmonitor/static/755.b0c8069fab2b94b3c4ac.js.LICENSE.txt
jupyterlab_sparkmonitor-4.1.0.data/data/share/jupyter/labextensions/jupyterlab-sparkmonitor/static/762.628f41dcded307df0a05.js
jupyterlab_sparkmonitor-4.1.0.data/data/share/jupyter/labextensions/jupyterlab-sparkmonitor/static/762.628f41dcded307df0a05.js.LICENSE.txt
jupyterlab_sparkmonitor-4.1.0.data/data/share/jupyter/labextensions/jupyterlab-sparkmonitor/static/973.6265200f90b5a2024034.js
jupyterlab_sparkmonitor-4.1.0.data/data/share/jupyter/labextensions/jupyterlab-sparkmonitor/static/remoteEntry.c159dd96f3073f4fc5ff.js
jupyterlab_sparkmonitor-4.1.0.data/data/share/jupyter/labextensions/jupyterlab-sparkmonitor/static/style.js
jupyterlab_sparkmonitor-4.1.0.dist-info/LICENSE
jupyterlab_sparkmonitor-4.1.0.dist-info/METADATA
jupyterlab_sparkmonitor-4.1.0.dist-info/WHEEL
jupyterlab_sparkmonitor-4.1.0.dist-info/top_level.txt
jupyterlab_sparkmonitor-4.1.0.dist-info/RECORD
