Metadata-Version: 2.1
Name: jupyterlab-sparkmonitor
Version: 4.1.0
Summary: Spark Monitor Extension for Jupyter Lab
Home-page: https://github.com/itsjafer/jupyterlab-sparkmonitor#readme
Author: Krishnan R
Author-email: krishnanr1997@gmail.com
Maintainer: itsjafer
Maintainer-email: itsjafer@gmail.com
License: Apache-2.0
Keywords: Jupyter,JupyterLab,JupyterLab3
Platform: Linux
Platform: Mac OS X
Platform: Windows
Classifier: License :: OSI Approved :: BSD License
Classifier: Programming Language :: Python
Classifier: Programming Language :: Python :: 3
Classifier: Programming Language :: Python :: 3.6
Classifier: Programming Language :: Python :: 3.7
Classifier: Programming Language :: Python :: 3.8
Classifier: Programming Language :: Python :: 3.9
Classifier: Framework :: Jupyter
Requires-Python: >=3.6
License-File: LICENSE
Requires-Dist: bs4
Requires-Dist: tornado
Requires-Dist: jupyterlab (~=3.0)
Requires-Dist: jupyter-packaging (<2,~=0.9)
Provides-Extra: pyspark
Requires-Dist: pyspark (>3.0.0) ; extra == 'pyspark'
